{
  "main": {
    "id": "795cad99864b9828",
    "type": "split",
    "children": [
      {
        "id": "6a422bca563d2cd0",
        "type": "tabs",
        "children": [
          {
            "id": "c340083190100fc4",
            "type": "leaf",
            "pinned": true,
            "state": {
              "type": "markdown",
              "state": {
                "file": "Tabula Ortus.md",
                "mode": "preview",
                "source": false
              },
              "pinned": true,
              "icon": "lucide-file",
              "title": "Tabula Ortus"
            }
          },
          {
            "id": "09f6b35dfe2647bf",
            "type": "leaf",
            "state": {
              "type": "markdown",
              "state": {
                "file": "02. Corpus Mundi/U/useMemo.md",
                "mode": "source",
                "source": false
              },
              "icon": "lucide-file",
              "title": "useMemo"
            }
          },
          {
            "id": "6a4aa9c4d32397d7",
            "type": "leaf",
            "state": {
              "type": "markdown",
              "state": {
                "file": "01. Inbox/To Classify/Dual Write/Dual Write.md",
                "mode": "source",
                "source": false
              },
              "icon": "lucide-file",
              "title": "Dual Write"
            }
          },
          {
            "id": "0092f4946cd25e20",
            "type": "leaf",
            "state": {
              "type": "bases",
              "state": {
                "file": "02. Corpus Mundi/__02. Corpus Mundi.base",
                "viewName": "Table"
              },
              "icon": "lucide-table",
              "title": "__02. Corpus Mundi"
            }
          },
          {
            "id": "25c934cf771c9b74",
            "type": "leaf",
            "state": {
              "type": "markdown",
              "state": {
                "file": "02. Corpus Mundi/S/Syllogism.md",
                "mode": "source",
                "source": false
              },
              "icon": "lucide-file",
              "title": "Syllogism"
            }
          },
          {
            "id": "4fa3cec135bbe1b7",
            "type": "leaf",
            "state": {
              "type": "markdown",
              "state": {
                "file": "01. Inbox/To Classify/React/React Hooks Structure Proposal.md",
                "mode": "source",
                "source": false
              },
              "icon": "lucide-file",
              "title": "React Hooks Structure Proposal"
            }
          },
          {
            "id": "47ba9fe65eab8956",
            "type": "leaf",
            "state": {
              "type": "markdown",
              "state": {
                "file": "01. Inbox/To Classify/Event-Driven Architecture/Event-Driven Architecture Structure Proposal.md",
                "mode": "source",
                "source": false
              },
              "icon": "lucide-file",
              "title": "Event-Driven Architecture Structure Proposal"
            }
          },
          {
            "id": "4f31f8905eee2b77",
            "type": "leaf",
            "state": {
              "type": "markdown",
              "state": {
                "file": "01. Inbox/To Classify/React/React.memo.md",
                "mode": "source",
                "source": false
              },
              "icon": "lucide-file",
              "title": "React.memo"
            }
          }
        ],
        "currentTab": 7
      }
    ],
    "direction": "vertical"
  },
  "left": {
    "id": "46574ee1a15de66b",
    "type": "split",
    "children": [
      {
        "id": "0bb8e4317ca6bb26",
        "type": "tabs",
        "children": [
          {
            "id": "c3376d17abdf195f",
            "type": "leaf",
            "state": {
              "type": "file-explorer",
              "state": {
                "sortOrder": "alphabetical",
                "autoReveal": false
              },
              "icon": "lucide-folder-closed",
              "title": "Files"
            }
          },
          {
            "id": "1406480daf0e7c1c",
            "type": "leaf",
            "state": {
              "type": "search",
              "state": {
                "query": "git",
                "matchingCase": false,
                "explainSearch": false,
                "collapseAll": false,
                "extraContext": false,
                "sortOrder": "alphabetical"
              },
              "icon": "lucide-search",
              "title": "Search"
            }
          },
          {
            "id": "7ae1322a8a0939d6",
            "type": "leaf",
            "state": {
              "type": "bookmarks",
              "state": {},
              "icon": "lucide-bookmark",
              "title": "Bookmarks"
            }
          }
        ]
      }
    ],
    "direction": "horizontal",
    "width": 389.5
  },
  "right": {
    "id": "bc1652196a189fba",
    "type": "split",
    "children": [
      {
        "id": "24dadcd18c492942",
        "type": "tabs",
        "children": [
          {
            "id": "a41e7f466cc9d723",
            "type": "leaf",
            "state": {
              "type": "outline",
              "state": {
                "file": "01. Inbox/To Classify/React/React.memo.md",
                "followCursor": false,
                "showSearch": false,
                "searchQuery": ""
              },
              "icon": "lucide-list",
              "title": "Outline of React.memo"
            }
          },
          {
            "id": "71a0b60a9f3ca7eb",
            "type": "leaf",
            "state": {
              "type": "outgoing-link",
              "state": {
                "file": "Home.md",
                "linksCollapsed": false,
                "unlinkedCollapsed": true
              },
              "icon": "links-going-out",
              "title": "Outgoing links from Home"
            }
          },
          {
            "id": "fd143b5dd6dad9e9",
            "type": "leaf",
            "state": {
              "type": "backlink",
              "state": {
                "file": "06 - Software Development/Golang/Go без воды (Ченский Леонид)/02.06.02. Структуры. Методы.md",
                "collapseAll": true,
                "extraContext": false,
                "sortOrder": "alphabetical",
                "showSearch": false,
                "searchQuery": "",
                "backlinkCollapsed": false,
                "unlinkedCollapsed": true
              },
              "icon": "links-coming-in",
              "title": "Backlinks for 02.06.02. Структуры. Методы"
            }
          },
          {
            "id": "580cf01320f8d832",
            "type": "leaf",
            "state": {
              "type": "tag",
              "state": {
                "sortOrder": "frequency",
                "useHierarchy": true,
                "showSearch": false,
                "searchQuery": ""
              },
              "icon": "lucide-tags",
              "title": "Tags"
            }
          },
          {
            "id": "eec95473fd789401",
            "type": "leaf",
            "state": {
              "type": "git-view",
              "state": {},
              "icon": "lucide-ghost",
              "title": "git-view"
            }
          },
          {
            "id": "b697f0273bdfec95",
            "type": "leaf",
            "state": {
              "type": "juggl_nodes",
              "state": {},
              "icon": "ag-node-list",
              "title": "Juggl nodes"
            }
          },
          {
            "id": "e4924f39d6f128de",
            "type": "leaf",
            "state": {
              "type": "juggl_style",
              "state": {},
              "icon": "ag-style",
              "title": "Juggl style"
            }
          }
        ]
      }
    ],
    "direction": "horizontal",
    "width": 407.5
  },
  "left-ribbon": {
    "hiddenItems": {
      "switcher:Open quick switcher": false,
      "graph:Open graph view": false,
      "canvas:Create new canvas": false,
      "daily-notes:Open today's daily note": false,
      "templates:Insert template": false,
      "command-palette:Open command palette": false,
      "bases:Create new base": false,
      "dashboard-navigator:Open dashboard navigator": false,
      "obsidian-excalidraw-plugin:New drawing": false,
      "obsidian-git:Open Git source control": false,
      "iconic:Open rulebook": false,
      "obsidian-local-images-plus:Local Images Plus  0.16.4\r\nLocalize attachments (plugin folder)": false,
      "mermaid-tools:Open Mermaid Toolbar": false,
      "table-editor-obsidian:Advanced Tables Toolbar": false,
      "custom-sort:Toggle custom sorting": false,
      "templater-obsidian:Templater": false,
      "juggl:Juggl global graph": false
    }
  },
  "active": "4f31f8905eee2b77",
  "lastOpenFiles": [
    "Tabula Ortus.md",
    "02. Corpus Mundi/U/useMemo.md",
    "01. Inbox/To Classify/React/React Component Re-renders.md",
    "01. Inbox/To Classify/React/React State Updates.md",
    "01. Inbox/To Classify/React/React Reconciliation.md",
    "01. Inbox/To Classify/React/React Render.md",
    "01. Inbox/To Classify/React/React.memo.md",
    "01. Inbox/To Classify/Browser Loading Hints/Script Loading Attributes.md",
    "01. Inbox/To Classify/Browser Loading Hints/Resource Hints.md",
    "01. Inbox/To Classify/Browser Loading Hints/Preload.md",
    "01. Inbox/To Classify/Browser Loading Hints/Prefetch.md",
    "01. Inbox/To Classify/Browser Loading Hints/Modulepreload.md",
    "01. Inbox/To Classify/Browser Loading Hints/Defer Script.md",
    "01. Inbox/To Classify/Browser Loading Hints/Browser Loading Hints.md",
    "01. Inbox/To Classify/Browser Loading Hints/Browser Loading Hints Structure Proposal.md",
    "01. Inbox/To Classify/Browser Loading Hints/Async Script.md",
    "01. Inbox/To Classify/Browser Loading Hints",
    "01. Inbox/To Classify/CORS/Preflight Request.md",
    "01. Inbox/To Classify/CORS/CORS Structure Proposal.md",
    "01. Inbox/To Classify/CORS/Web Origin Model.md",
    "01. Inbox/To Classify/CORS/Web Origin.md",
    "01. Inbox/To Classify/CORS/Same-Origin Policy.md",
    "01. Inbox/To Classify/CORS/Credentialed CORS Requests.md",
    "01. Inbox/To Classify/CORS/CORS.md",
    "01. Inbox/To Classify/CORS/CORS Response Headers.md",
    "01. Inbox/To Classify/CORS/CORS Request Headers.md",
    "01. Inbox/To Classify/CORS",
    "01. Inbox/To Classify/Distributed Systems Problems/Distributed Systems Problems.md",
    "01. Inbox/To Classify/Taxonomy",
    "01. Inbox/To Classify/Automata Theory",
    "01. Inbox/To Classify/Finite Automaton",
    "03. Maps and Courses/Topic Maps/DBMS/ACID as transactional semantic guarantees.canvas",
    "01. Inbox/To Classify/Golang",
    "03. Maps and Courses/Topic Maps/DBMS/PostgreSQL Architecture.canvas",
    "03. Maps and Courses/Topic Maps/DBMS/DBMS.base",
    "03. Maps and Courses/Topic Maps/Javascript/JavaScript.base",
    "02. Corpus Mundi/__02. Corpus Mundi.base",
    "01. Inbox/To Classify/Semantics",
    "03. Maps and Courses/Topic Maps/DBMS/_resources/01-dbms-architecture.jpg",
    "01. Inbox/To Classify/Dual Write/_resources/dua-write.jpg",
    "Pasted image 20260314213657.png",
    "00. Obsidian Praxis/Config & Settings Details/Images/gruvbox_colors.png",
    "Databases/Database Internals (Petrov Alex)/_resources/01-architecture-of-dbms.jpg",
    "dbin_0101.png",
    "System Design/Grokking System Design Fundamentals (DesignGurus)/05. Domain Name System (DNS)/_resources/3cc11f4df2c7923a0af25481d7c62fc3_MD5.webp",
    "Electronics/RaspberryPI/Untitled.canvas",
    "CS Dashboard/00. canvas/CS/cs prog paradigms.canvas",
    "CS Dashboard/00. canvas/cs design patterns.canvas",
    "Golang Dashboard/00. canvas/00 - Go/types/go types.canvas",
    "Memes/Memes.canvas",
    "06E6E3~1.SOF/Golang/Observabiltiy как в Bigtech/Observaibity.canvas",
    "Golang Dashboard/00. Legend/vc.ru, Senior Go Developer/00. CV & Legend/_resources/01-Legend vc.ru.canvas",
    "01. Go Dashboard/00. Legend/MindTrust, Senior Go Developer/Legend.canvas"
  ]
}